rackio_admin/__init__.py
rackio_admin/_singleton.py
rackio_admin/core.py
rackio_admin/example.py
rackio_admin/resources.py
rackio_admin/tools.py
rackio_admin/static/css/bootstrap-datetimepicker.min.css
rackio_admin/static/css/font-face.css
rackio_admin/static/css/theme.css
rackio_admin/static/fonts/poppins/poppins-v5-latin-100.eot
rackio_admin/static/fonts/poppins/poppins-v5-latin-100.svg
rackio_admin/static/fonts/poppins/poppins-v5-latin-100.ttf
rackio_admin/static/fonts/poppins/poppins-v5-latin-100.woff
rackio_admin/static/fonts/poppins/poppins-v5-latin-100.woff2
rackio_admin/static/fonts/poppins/poppins-v5-latin-100italic.eot
rackio_admin/static/fonts/poppins/poppins-v5-latin-100italic.svg
rackio_admin/static/fonts/poppins/poppins-v5-latin-100italic.ttf
rackio_admin/static/fonts/poppins/poppins-v5-latin-100italic.woff
rackio_admin/static/fonts/poppins/poppins-v5-latin-100italic.woff2
rackio_admin/static/fonts/poppins/poppins-v5-latin-200.eot
rackio_admin/static/fonts/poppins/poppins-v5-latin-200.svg
rackio_admin/static/fonts/poppins/poppins-v5-latin-200.ttf
rackio_admin/static/fonts/poppins/poppins-v5-latin-200.woff
rackio_admin/static/fonts/poppins/poppins-v5-latin-200.woff2
rackio_admin/static/fonts/poppins/poppins-v5-latin-200italic.eot
rackio_admin/static/fonts/poppins/poppins-v5-latin-200italic.svg
rackio_admin/static/fonts/poppins/poppins-v5-latin-200italic.ttf
rackio_admin/static/fonts/poppins/poppins-v5-latin-200italic.woff
rackio_admin/static/fonts/poppins/poppins-v5-latin-200italic.woff2
rackio_admin/static/fonts/poppins/poppins-v5-latin-300.eot
rackio_admin/static/fonts/poppins/poppins-v5-latin-300.svg
rackio_admin/static/fonts/poppins/poppins-v5-latin-300.ttf
rackio_admin/static/fonts/poppins/poppins-v5-latin-300.woff
rackio_admin/static/fonts/poppins/poppins-v5-latin-300.woff2
rackio_admin/static/fonts/poppins/poppins-v5-latin-300italic.eot
rackio_admin/static/fonts/poppins/poppins-v5-latin-300italic.svg
RackioAdmin-0.5.dist-info/LICENSE
RackioAdmin-0.5.dist-info/METADATA
RackioAdmin-0.5.dist-info/WHEEL
RackioAdmin-0.5.dist-info/top_level.txt
RackioAdmin-0.5.dist-info/RECORD
